rootfinding.py
rootfinding-1.0.4.dist-info/licenses/LICENSE.txt
rootfinding-1.0.4.dist-info/METADATA
rootfinding-1.0.4.dist-info/WHEEL
rootfinding-1.0.4.dist-info/top_level.txt
rootfinding-1.0.4.dist-info/RECORD
