Metadata-Version: 2.4
Name: rootfinding
Version: 1.0.4
Summary: Find roots of scalar functions
Home-page: https://github.com/gerlero/rootfinding
Author: Gabriel S. Gerlero
Author-email: ggerlero@cimec.unl.edu.ar
Project-URL: Documentation, https://rootfinding.readthedocs.io
Project-URL: Bug Tracker, https://github.com/gerlero/rootfinding/issues
Classifier: Development Status :: 7 - Inactive
Classifier: Intended Audience :: Developers
Classifier: Intended Audience :: Science/Research
Classifier: License :: OSI Approved :: BSD License
Classifier: Programming Language :: Python
Classifier: Programming Language :: Python :: 2.7
Classifier: Programming Language :: Python :: 3
Classifier: Topic :: Scientific/Engineering :: Mathematics
Classifier: Topic :: Software Development :: Libraries
Classifier: Operating System :: OS Independent
Requires-Python: !=3.0.*,!=3.1.*,!=3.2.*,!=3.3.*,!=3.4.*,>=2.7
License-File: LICENSE.txt
Provides-Extra: test
Requires-Dist: pytest-cov; extra == "test"
Requires-Dist: check-manifest; extra == "test"
Provides-Extra: doc
Requires-Dist: sphinx; extra == "doc"
Requires-Dist: sphinx_rtd_theme; extra == "doc"
Provides-Extra: dev
Requires-Dist: pytest-cov; extra == "dev"
Requires-Dist: check-manifest; extra == "dev"
Requires-Dist: sphinx; extra == "dev"
Requires-Dist: sphinx_rtd_theme; extra == "dev"
Dynamic: license-file
